README.rst
setup.py
mfnbc/__init__.py
mfnbc.egg-info/PKG-INFO
mfnbc.egg-info/SOURCES.txt
mfnbc.egg-info/dependency_links.txt
mfnbc.egg-info/not-zip-safe
mfnbc.egg-info/pbr.json
mfnbc.egg-info/requires.txt
mfnbc.egg-info/top_level.txt
test/test_mfnbc.py