Metadata-Version: 1.1
Name: mfnbc
Version: 1.91
Summary: UNKNOWN
Home-page: https://github.com/shawnzam/mfnbc
Author: Shawn
Author-email: shawnzam@gmail.com
License: The MIT License (MIT)
Keywords: bayes
Platform: UNKNOWN
Classifier: Programming Language :: Python :: 3
Classifier: Natural Language :: English
Classifier: Topic :: Scientific/Engineering :: Information Analysis
